shipyard_email/__init__.py
shipyard_email/email_client.py
shipyard_email/exceptions.py
shipyard_email/cli/__init__.py
shipyard_email/cli/authtest.py
shipyard_email/cli/send_conditional_email.py
shipyard_email/cli/send_email.py
shipyard_email/cli/send_email_with_file.py
shipyard_email-0.3.1.dist-info/METADATA
shipyard_email-0.3.1.dist-info/WHEEL
shipyard_email-0.3.1.dist-info/top_level.txt
shipyard_email-0.3.1.dist-info/RECORD
