Metadata-Version: 2.4
Name: shipyard-email
Version: 0.3.1
Summary: Simplified blueprints for building data pipelines with Email
Requires-Python: >=3.11
Requires-Dist: shipyard-bp-utils==1.3.1a0
Requires-Dist: shipyard-templates>=0.6.2
Requires-Dist: typing-extensions>=4.11.0
